groupbyScore/groupbyScore.py
groupbyscore-0.0.5.dist-info/licenses/LICENSE
groupbyscore-0.0.5.dist-info/METADATA
groupbyscore-0.0.5.dist-info/WHEEL
groupbyscore-0.0.5.dist-info/top_level.txt
groupbyscore-0.0.5.dist-info/RECORD
