Metadata-Version: 2.4
Name: groupbyScore
Version: 0.0.5
Summary: You can group similar items (e.g., strings or dict fields) using the fuzzywuzzy package by comparing their similarity scores.
Author-email: Example Author <author@example.com>
License-Expression: MIT
Project-URL: Homepage, https://github.com/postboxat18/groupbyScore.git
Classifier: Programming Language :: Python :: 3.12
Classifier: Operating System :: OS Independent
Requires-Python: >=3.9
License-File: LICENSE
Dynamic: license-file
